convertbase/__init__.py
convertbase/baseconverter.py
convertbase/convertbase.py
convertbase-0.1.3.dist-info/LICENSE
convertbase-0.1.3.dist-info/METADATA
convertbase-0.1.3.dist-info/WHEEL
convertbase-0.1.3.dist-info/top_level.txt
convertbase-0.1.3.dist-info/RECORD
