Metadata-Version: 2.1
Name: convertbase
Version: 0.1.3
Summary: Convert between bases, initailly intended for RFC4648 base32
Home-page: https://github.com/johan-lahti/convertbase
Author: Johan Lahti
Author-email: ccie60702@gmail.com
License: UNKNOWN
Platform: UNKNOWN
Classifier: Programming Language :: Python :: 3
Classifier: License :: OSI Approved :: MIT License
Classifier: Operating System :: OS Independent
Requires-Python: >=3.7
